utpd_models_api/__init__.py
utpd_models_api/checkin_recent.py
utpd_models_api/common.py
utpd_models_api/py.typed
utpd_models_api/user_beers.py
utpd_models_api/user_checkins.py
utpd_models_api/user_friends.py
utpd_models_api/user_info.py
utpd_models_api-0.3.1.dist-info/METADATA
utpd_models_api-0.3.1.dist-info/WHEEL
utpd_models_api-0.3.1.dist-info/RECORD
